point/__init__.py
point-0.0.1.dist-info/DESCRIPTION.rst
point-0.0.1.dist-info/METADATA
point-0.0.1.dist-info/RECORD
point-0.0.1.dist-info/WHEEL
point-0.0.1.dist-info/metadata.json
point-0.0.1.dist-info/top_level.txt
tests/__init__.py
